mojito/__init__.py
mojito/app.py
mojito/auth.py
mojito/config.py
mojito/forms.py
mojito/globals.py
mojito/helpers.py
mojito/message_flash.py
mojito/middleware/user_sessions.py
mojito/py.typed
mojito/requests.py
mojito/responses.py
mojito/routing.py
mojito/staticfiles.py
mojito/templating.py
mojito/testclient.py
mojito/websockets.py
mojito_web-0.2.0.dist-info/METADATA
mojito_web-0.2.0.dist-info/WHEEL
mojito_web-0.2.0.dist-info/entry_points.txt
mojito_web-0.2.0.dist-info/RECORD
